honeybee_energy_ph/README.md
honeybee_energy_ph/__init__.py
honeybee_energy_ph/_extend_honeybee_energy_ph.py
honeybee_energy_ph/boundarycondition.py
honeybee_energy_ph/construction/__init__.py
honeybee_energy_ph/construction/_base.py
honeybee_energy_ph/construction/thermal_bridge.py
honeybee_energy_ph/construction/window.py
honeybee_energy_ph/hvac/__init__.py
honeybee_energy_ph/hvac/_base.py
honeybee_energy_ph/hvac/ducting.py
honeybee_energy_ph/hvac/fuels.py
honeybee_energy_ph/hvac/heat_pumps.py
honeybee_energy_ph/hvac/heating.py
honeybee_energy_ph/hvac/hot_water.py
honeybee_energy_ph/hvac/renewable_devices.py
honeybee_energy_ph/hvac/supportive_device.py
honeybee_energy_ph/hvac/ventilation.py
honeybee_energy_ph/library/__init__.py
honeybee_energy_ph/library/programtypes.py
honeybee_energy_ph/load/__init__.py
honeybee_energy_ph/load/_base.py
honeybee_energy_ph/load/_ph_equip_types.py
honeybee_energy_ph/load/ph_equipment.py
honeybee_energy_ph/load/phius_mf.py
honeybee_energy_ph/load/phius_residential.py
honeybee_energy_ph/properties/__init__.py
honeybee_energy_ph/properties/ruleset.py
honeybee_energy_ph/properties/space.py
honeybee_energy_ph/properties/construction/__init__.py
honeybee_energy_ph/properties/construction/air.py
honeybee_energy_ph/properties/construction/opaque.py
honeybee_energy_ph/properties/construction/window.py
honeybee_energy_ph/properties/construction/windowshade.py
honeybee_energy_ph/properties/hot_water/__init__.py
honeybee_energy_ph/properties/hot_water/hw_program.py
honeybee_energy_ph/properties/hot_water/hw_system.py
honeybee_energy_ph/properties/hvac/__init__.py
honeybee_energy_ph/properties/hvac/allair.py
honeybee_energy_ph/properties/hvac/doas.py
honeybee_energy_ph/properties/hvac/heatcool.py
honeybee_energy_ph/properties/hvac/idealair.py
honeybee_energy_ph/properties/load/__init__.py
honeybee_energy_ph/properties/load/equipment.py
honeybee_energy_ph/properties/load/lighting.py
honeybee_energy_ph/properties/load/people.py
honeybee_ph-1.32.0.dist-info/licenses/LICENSE
honeybee_ph-1.32.0.dist-info/METADATA
honeybee_ph-1.32.0.dist-info/WHEEL
honeybee_ph-1.32.0.dist-info/top_level.txt
honeybee_ph-1.32.0.dist-info/RECORD
