Metadata-Version: 2.4
Name: honeybee_ph
Version: 1.32.0
Summary: Plugin for Honeybee to enable Passive House modeling.
Home-page: https://github.com/PH-Tools/honeybee_ph
Author: PH-Tools
Author-email: phtools@bldgtyp.com
License: GPLv3+
Classifier: Programming Language :: Python :: 2
Classifier: Programming Language :: Python :: 2.7
Classifier: Programming Language :: Python :: 3
Classifier: Programming Language :: Python :: 3.10
Classifier: Programming Language :: Python :: Implementation :: CPython
Classifier: License :: OSI Approved :: GNU General Public License v3 or later (GPLv3+)
Classifier: Operating System :: OS Independent
Classifier: Typing :: Typed
License-File: LICENSE
Requires-Dist: honeybee-core>=1.64.9
Requires-Dist: honeybee-energy>=1.116.103
Requires-Dist: PH-units>=1.5.26
Dynamic: description
Dynamic: description-content-type
Dynamic: license-file
Dynamic: requires-dist
